{"stats":{"minecraft:custom":{"minecraft:jump":58,"minecraft:time_since_rest":5192,"minecraft:leave_game":1,"minecraft:crouch_one_cm":4,"minecraft:damage_dealt":140,"minecraft:sprint_one_cm":12403,"minecraft:play_time":5192,"minecraft:damage_taken":60,"minecraft:time_since_death":5192,"minecraft:walk_one_cm":4977,"minecraft:sneak_time":8,"minecraft:total_world_time":5192,"minecraft:mob_kills":4,"minecraft:fall_one_cm":836,"minecraft:fly_one_cm":20086},"minecraft:mined":{"minecraft:spruce_log":1,"minecraft:dirt":1},"minecraft:crafted":{"minecraft:spruce_planks":4,"minecraft:stick":4},"minecraft:killed":{"minecraft:slime":4},"minecraft:picked_up":{"minecraft:spruce_log":1,"minecraft:sweet_berries":3,"minecraft:slime_ball":8,"minecraft:dirt":1}},"DataVersion":3465}