{"stats":{"minecraft:broken":{"minecraft:iron_leggings":2,"minecraft:diamond_shovel":15,"minecraft:shield":1,"minecraft:golden_boots":1,"minecraft:iron_boots":5,"minecraft:iron_chestplate":1,"minecraft:golden_sword":1,"minecraft:iron_helmet":6,"minecraft:golden_chestplate":1,"minecraft:flint_and_steel":2,"minecraft:golden_pickaxe":1},"minecraft:dropped":{"minecraft:iron_sword":16,"minecraft:pink_stained_glass":2,"minecraft:porkchop":57,"minecraft:respawn_anchor":61,"minecraft:lapis_lazuli":1633,"minecraft:chorus_fruit":106,"minecraft:glass_bottle":487,"minecraft:diamond":1795,"minecraft:crafting_table":12,"minecraft:lime_concrete_powder":10443,"minecraft:lime_stained_glass":3,"minecraft:cooked_porkchop":1640,"minecraft:pitcher_pod":1,"minecraft:dark_oak_slab":4,"minecraft:weeping_vines":16,"minecraft:glow_berries":4,"minecraft:warped_roots":3697,"minecraft:cracked_stone_bricks":17,"minecraft:quartz_pillar":38,"minecraft:red_mushroom":52,"minecraft:gold_block":341,"minecraft:emerald":260,"minecraft:gray_concrete":190,"minecraft:birch_fence":3,"minecraft:dark_oak_fence":56,"minecraft:conduit":816,"minecraft:dark_oak_trapdoor":6,"minecraft:tnt_minecart":4,"minecraft:netherite_boots":7,"minecraft:gold_nugget":253,"minecraft:writable_book":4,"minecraft:acacia_fence_gate":2,"minecraft:sand":48062,"minecraft:dark_oak_planks":22,"minecraft:fishing_rod":3,"minecraft:white_wool":175,"minecraft:diorite_slab":3,"minecraft:goat_horn":1,"minecraft:diamond_block":2546,"minecraft:ancient_debris":145,"minecraft:lever":70,"minecraft:iron_nugget":1901,"minecraft:cooked_chicken":22,"minecraft:cobbled_deepslate":2110,"minecraft:tinted_glass":2,"minecraft:netherite_sword":29,"minecraft:wheat":218,"minecraft:obsidian":140,"minecraft:rotten_flesh":11128,"minecraft:oak_planks":5507,"minecraft:glowstone_dust":62,"minecraft:quartz_bricks":5,"minecraft:nether_brick_fence":3,"minecraft:azure_bluet":259,"minecraft:warped_planks":18,"minecraft:waxed_copper_block":1,"minecraft:wind_charge":6,"minecraft:endermite_spawn_egg":1,"minecraft:red_mushroom_block":1,"minecraft:sea_lantern":1,"minecraft:coal_ore":124,"minecraft:diorite_wall":6,"minecraft:quartz_block":3595,"minecraft:jungle_log":9,"minecraft:music_disc_mall":2,"minecraft:leather_boots":10,"minecraft:leather_leggings":2,"minecraft:glass":3896,"minecraft:warped_wart_block":12,"minecraft:stone_brick_stairs":24,"minecraft:dead_brain_coral_fan":2,"minecraft:cartography_table":384,"minecraft:golden_boots":7,"minecraft:black_dye":2,"minecraft:wheat_seeds":938,"minecraft:clock":77,"minecraft:smooth_quartz_stairs":32,"minecraft:dripstone_block":107,"minecraft:netherite_chestplate":4,"minecraft:end_stone_brick_slab":1806,"minecraft:book":1144,"minecraft:prismarine_crystals":30,"minecraft:waxed_copper_grate":2,"minecraft:red_stained_glass":1,"minecraft:mushroom_stew":3,"minecraft:golden_apple":339,"minecraft:coal_block":321,"minecraft:lava_bucket":25,"minecraft:cobweb":3,"minecraft:stripped_crimson_stem":1,"minecraft:gray_wool":9,"minecraft:ink_sac":44,"minecraft:blackstone_wall":64,"minecraft:wooden_axe":3,"minecraft:cooked_salmon":65,"minecraft:potion":10,"minecraft:oak_stairs":6,"minecraft:pumpkin":44,"minecraft:white_banner":15,"minecraft:red_dye":61,"minecraft:smooth_stone":17043,"minecraft:chipped_anvil":3124,"minecraft:chainmail_leggings":4,"minecraft:smooth_sandstone":191,"minecraft:blue_carpet":3,"minecraft:trapped_chest":2,"minecraft:lily_pad":5,"minecraft:stone_brick_slab":26,"minecraft:snow_block":595,"minecraft:creeper_head":124,"minecraft:soul_soil":18,"minecraft:netherite_hoe":4,"minecraft:green_terracotta":3,"minecraft:light_blue_glazed_terracotta":31,"minecraft:player_head":3,"minecraft:cocoa_beans":949,"minecraft:sticky_piston":62,"minecraft:experience_bottle":248,"minecraft:white_carpet":5028,"minecraft:clay_ball":27,"minecraft:iron_boots":15,"minecraft:damaged_anvil":3,"minecraft:name_tag":8,"minecraft:light_gray_concrete":48,"minecraft:white_shulker_box":9,"minecraft:white_terracotta":7,"minecraft:end_stone_brick_wall":64,"minecraft:oak_sign":12,"minecraft:shears":12,"minecraft:blast_furnace":3,"minecraft:diamond_sword":22,"minecraft:spruce_boat":1,"minecraft:sea_pickle":2,"minecraft:piglin_banner_pattern":1,"minecraft:peony":103,"minecraft:spruce_trapdoor":6,"minecraft:spruce_planks":165,"minecraft:diamond_pickaxe":30,"minecraft:light_blue_carpet":2,"minecraft:pink_shulker_box":8,"minecraft:small_dripleaf":59,"minecraft:redstone_torch":40,"minecraft:stone_bricks":127,"minecraft:barrel":105,"minecraft:bamboo":645,"minecraft:sandstone":705,"minecraft:bow":52,"minecraft:red_sand":89,"minecraft:magma_block":1422,"minecraft:cooked_rabbit":113,"minecraft:terracotta":62,"minecraft:nether_brick_stairs":7,"minecraft:shulker_spawn_egg":3,"minecraft:blue_shulker_box":2,"minecraft:daylight_detector":5,"minecraft:bamboo_trapdoor":2,"minecraft:soul_sand":118,"minecraft:candle":36,"minecraft:moss_block":2363,"minecraft:orange_dye":124,"minecraft:warped_fungus":421,"minecraft:oak_log":1581,"minecraft:golden_pickaxe":4,"minecraft:ender_pearl":7795,"minecraft:nether_star":66,"minecraft:jungle_hanging_sign":1,"minecraft:lime_terracotta":4,"minecraft:leather":156,"minecraft:chest_minecart":1,"minecraft:honeycomb":5,"minecraft:jungle_planks":17,"minecraft:iron_horse_armor":1,"minecraft:mossy_cobblestone_wall":1,"minecraft:bedrock":26,"minecraft:black_banner":1,"minecraft:birch_slab":84,"minecraft:host_armor_trim_smithing_template":2,"minecraft:cod":17,"minecraft:cobblestone_stairs":1,"minecraft:redstone_lamp":3,"minecraft:mace":8,"minecraft:dark_oak_log":19,"minecraft:packed_ice":5052,"minecraft:ice":41,"minecraft:polished_blackstone_pressure_plate":128,"minecraft:mutton":68,"minecraft:snowball":242,"minecraft:prismarine_brick_slab":2,"minecraft:wet_sponge":1,"minecraft:dead_bubble_coral_fan":2,"minecraft:tube_coral":1,"minecraft:black_concrete":11490,"minecraft:cauldron":11,"minecraft:gold_ingot":377,"minecraft:pink_terracotta":1001,"minecraft:purpur_block":513,"minecraft:spyglass":16,"minecraft:pillager_spawn_egg":3,"minecraft:cherry_stairs":2,"minecraft:chiseled_tuff_bricks":2,"minecraft:soul_lantern":8,"minecraft:pointed_dripstone":37,"minecraft:beetroot":189,"minecraft:mossy_stone_brick_slab":4,"minecraft:yellow_stained_glass":1,"minecraft:cooked_mutton":423,"minecraft:acacia_stairs":3,"minecraft:ward_armor_trim_smithing_template":2,"minecraft:birch_fence_gate":8,"minecraft:mushroom_stem":11,"minecraft:leather_chestplate":6,"minecraft:trident":6,"minecraft:dune_armor_trim_smithing_template":2,"minecraft:oak_wood":187,"minecraft:dropper":11,"minecraft:ochre_froglight":837,"minecraft:beetroot_seeds":3,"minecraft:stone_brick_wall":6,"minecraft:acacia_slab":2,"minecraft:iron_ore":24,"minecraft:birch_button":2,"minecraft:iron_bars":131,"minecraft:scaffolding":52,"minecraft:splash_potion":2,"minecraft:bread":118,"minecraft:vine":2,"minecraft:golden_helmet":4,"minecraft:lilac":82,"minecraft:yellow_concrete":29,"minecraft:netherite_axe":23,"minecraft:mangrove_propagule":1,"minecraft:golden_axe":5,"minecraft:amethyst_block":162,"minecraft:piglin_head":1,"minecraft:activator_rail":3,"minecraft:tropical_fish":134,"minecraft:spruce_stairs":24,"minecraft:cherry_fence_gate":1,"minecraft:spruce_fence_gate":4,"minecraft:iron_block":623,"minecraft:black_candle":2,"minecraft:pearlescent_froglight":1,"minecraft:milk_bucket":1,"minecraft:green_dye":1,"minecraft:repeater":37,"minecraft:nether_wart_block":112,"minecraft:white_concrete":85,"minecraft:melon_slice":1062,"minecraft:yellow_shulker_box":1,"minecraft:zombie_head":62,"minecraft:light_gray_stained_glass":2040,"minecraft:crimson_sign":1,"minecraft:fire_charge":2,"minecraft:pink_banner":80,"minecraft:jungle_leaves":1,"minecraft:polished_blackstone_brick_slab":64,"minecraft:stonecutter":2,"minecraft:raw_iron_block":16,"minecraft:cactus":170,"minecraft:light_blue_stained_glass_pane":1,"minecraft:tripwire_hook":3,"minecraft:redstone_block":274,"minecraft:blue_terracotta":18695,"minecraft:kelp":1092,"minecraft:sweet_berries":2288,"minecraft:oak_trapdoor":10,"minecraft:dragon_head":64,"minecraft:wild_armor_trim_smithing_template":2,"minecraft:light_gray_terracotta":3,"minecraft:lime_concrete":865,"minecraft:guster_banner_pattern":1,"minecraft:tall_grass":4,"minecraft:wayfinder_armor_trim_smithing_template":2,"minecraft:villager_spawn_egg":1,"minecraft:comparator":18,"minecraft:bamboo_sign":1,"minecraft:stripped_oak_log":117,"minecraft:dirt_path":4160,"minecraft:shulker_box":271,"minecraft:netherite_leggings":5,"minecraft:flint_and_steel":32,"minecraft:light":14,"minecraft:copper_ore":2,"minecraft:bamboo_raft":1,"minecraft:gray_terracotta":1,"minecraft:end_stone_brick_stairs":64,"minecraft:oak_button":26,"minecraft:dead_tube_coral_fan":5,"minecraft:netherite_block":127,"minecraft:andesite":5135,"minecraft:golden_leggings":3,"minecraft:oak_sapling":366,"minecraft:end_portal_frame":2,"minecraft:birch_sign":27,"minecraft:spruce_log":118,"minecraft:wooden_pickaxe":3,"minecraft:magma_cream":2,"minecraft:light_blue_terracotta":11,"minecraft:nautilus_shell":62,"minecraft:amethyst_cluster":4,"minecraft:brick":51,"minecraft:magenta_terracotta":1,"minecraft:crimson_stem":20,"minecraft:clay":23901,"minecraft:piston":115,"minecraft:short_grass":70,"minecraft:ominous_bottle":2,"minecraft:oak_pressure_plate":64,"minecraft:cooked_beef":344,"minecraft:spore_blossom":62,"minecraft:crossbow":21,"minecraft:orange_tulip":1,"minecraft:glow_item_frame":6,"minecraft:warped_hyphae":10,"minecraft:cherry_hanging_sign":1,"minecraft:mossy_stone_brick_stairs":6,"minecraft:fletching_table":320,"minecraft:saddle":4,"minecraft:purpur_stairs":256,"minecraft:silence_armor_trim_smithing_template":1,"minecraft:elytra":6,"minecraft:rail":1291,"minecraft:dragon_breath":571,"minecraft:cut_sandstone_slab":122,"minecraft:leather_helmet":4,"minecraft:sentry_armor_trim_smithing_template":2,"minecraft:red_carpet":717,"minecraft:item_frame":145,"minecraft:light_weighted_pressure_plate":448,"minecraft:red_shulker_box":7,"minecraft:packed_mud":2,"minecraft:dirt":1201,"minecraft:raw_copper_block":64,"minecraft:stone_button":68,"minecraft:yellow_dye":1310,"minecraft:large_fern":1,"minecraft:scrape_pottery_sherd":4,"minecraft:snout_armor_trim_smithing_template":2,"minecraft:jack_o_lantern":704,"minecraft:cherry_button":1,"minecraft:chain":89,"minecraft:bone_meal":8302,"minecraft:bone_block":541,"minecraft:sunflower":1,"minecraft:phantom_membrane":4,"minecraft:sugar":328,"minecraft:iron_pickaxe":7,"minecraft:polished_blackstone_slab":64,"minecraft:gray_dye":1,"minecraft:end_crystal":87,"minecraft:bone":2721,"minecraft:oak_door":1,"minecraft:pink_concrete":1308,"minecraft:note_block":6,"minecraft:magenta_banner":6,"minecraft:emerald_block":1039,"minecraft:sugar_cane":94394,"minecraft:polished_andesite_slab":3,"minecraft:bamboo_chest_raft":7,"minecraft:golden_chestplate":4,"minecraft:detector_rail":16,"minecraft:cut_red_sandstone_slab":65,"minecraft:birch_sapling":83,"minecraft:deepslate_brick_slab":1,"minecraft:enchanted_golden_apple":191,"minecraft:netherite_shovel":1,"minecraft:end_stone":4638,"minecraft:white_bed":6,"minecraft:salmon":92,"minecraft:orange_stained_glass":1,"minecraft:eye_armor_trim_smithing_template":2,"minecraft:tipped_arrow":526,"minecraft:deepslate_tiles":1,"minecraft:raiser_armor_trim_smithing_template":1,"minecraft:deepslate_copper_ore":1,"minecraft:charcoal":77,"minecraft:honey_block":18,"minecraft:hopper":329,"minecraft:ladder":49,"minecraft:spruce_slab":12,"minecraft:white_dye":19,"minecraft:end_stone_bricks":330,"minecraft:campfire":3,"minecraft:crying_obsidian":88,"minecraft:ghast_tear":331,"minecraft:white_glazed_terracotta":7,"minecraft:cherry_fence":2,"minecraft:lectern":65,"minecraft:egg":41,"minecraft:crimson_planks":3,"minecraft:enchanted_book":255,"minecraft:iron_ingot":91699,"minecraft:netherite_pickaxe":12,"minecraft:birch_leaves":4,"minecraft:copper_block":14,"minecraft:tnt":97,"minecraft:golden_horse_armor":1,"minecraft:oak_hanging_sign":49,"minecraft:netherite_helmet":4,"minecraft:iron_helmet":13,"minecraft:feather":155,"minecraft:purpur_slab":64,"minecraft:oak_fence":4,"minecraft:yellow_terracotta":1,"minecraft:barrier":6,"minecraft:cobblestone":68268,"minecraft:purple_concrete":5,"minecraft:apple":137,"minecraft:granite":201,"minecraft:command_block":4,"minecraft:purple_dye":8,"minecraft:disc_fragment_5":122,"minecraft:polished_blackstone_button":64,"minecraft:chainmail_helmet":3,"minecraft:coal":3112,"minecraft:pufferfish":5,"minecraft:end_rod":26,"minecraft:oxeye_daisy":265,"minecraft:spruce_hanging_sign":2,"minecraft:crimson_stairs":384,"minecraft:warped_slab":2,"minecraft:golden_carrot":73,"minecraft:iron_trapdoor":605,"minecraft:sponge":964,"minecraft:rose_bush":129,"minecraft:diamond_helmet":5,"minecraft:rib_armor_trim_smithing_template":2,"minecraft:dried_kelp":569,"minecraft:dead_bush":1,"minecraft:nether_sprouts":65,"minecraft:heart_of_the_sea":126,"minecraft:angler_pottery_sherd":2,"minecraft:iron_shovel":1,"minecraft:paper":10259,"minecraft:string":12979,"minecraft:spruce_sapling":174,"minecraft:pink_tulip":127,"minecraft:hanging_roots":1,"minecraft:purpur_pillar":256,"minecraft:furnace":209,"minecraft:moss_carpet":153,"minecraft:pitcher_plant":1,"minecraft:netherite_ingot":124,"minecraft:polished_diorite_slab":2,"minecraft:cobblestone_wall":4,"minecraft:smooth_stone_slab":1869,"minecraft:deepslate":189,"minecraft:bowl":8,"minecraft:diamond_hoe":8,"minecraft:suspicious_sand":1,"minecraft:chicken":11,"minecraft:blue_concrete":3,"minecraft:slime_block":5529,"minecraft:glow_lichen":76,"minecraft:magenta_concrete":251,"minecraft:light_blue_concrete":17633,"minecraft:diamond_ore":199,"minecraft:nether_bricks":4,"minecraft:spruce_fence":1,"minecraft:pumpkin_seeds":3,"minecraft:lily_of_the_valley":1,"minecraft:target":4,"minecraft:light_blue_dye":220,"minecraft:potato":1045,"minecraft:cobblestone_slab":6,"minecraft:shroomlight":6,"minecraft:stone":3683,"minecraft:allium":127,"minecraft:yellow_bed":1,"minecraft:carved_pumpkin":2,"minecraft:spider_eye":666,"minecraft:light_gray_dye":363,"minecraft:magenta_concrete_powder":45,"minecraft:blue_orchid":62,"minecraft:magenta_dye":38,"minecraft:red_tulip":66,"minecraft:bell":3,"minecraft:red_sandstone_stairs":3,"minecraft:magma_cube_spawn_egg":1,"minecraft:vex_armor_trim_smithing_template":2,"minecraft:pink_concrete_powder":63,"minecraft:black_wool":15,"minecraft:quartz_slab":70,"minecraft:birch_hanging_sign":1,"minecraft:crimson_nylium":59,"minecraft:warped_stem":1,"minecraft:birch_planks":2930,"minecraft:brown_mushroom":63,"minecraft:dark_oak_stairs":8,"minecraft:diamond_axe":13,"minecraft:baked_potato":223,"minecraft:decorated_pot":3,"minecraft:netherite_upgrade_smithing_template":5,"minecraft:tide_armor_trim_smithing_template":1,"minecraft:shaper_armor_trim_smithing_template":2,"minecraft:lantern":35,"minecraft:structure_void":1,"minecraft:flint":5068,"minecraft:spruce_leaves":14,"minecraft:cyan_terracotta":6,"minecraft:stripped_warped_hyphae":57,"minecraft:netherite_scrap":72,"minecraft:brush":4,"minecraft:dispenser":66,"minecraft:cornflower":46,"minecraft:crimson_roots":4056,"minecraft:coast_armor_trim_smithing_template":2,"minecraft:cooked_cod":22,"minecraft:white_stained_glass_pane":7,"minecraft:gilded_blackstone":56,"minecraft:amethyst_shard":51,"minecraft:polished_blackstone_bricks":3,"minecraft:glistering_melon_slice":6,"minecraft:acacia_door":1,"minecraft:birch_log":246,"minecraft:black_stained_glass":5,"minecraft:brown_mushroom_block":1,"minecraft:armor_stand":19,"minecraft:honeycomb_block":4,"minecraft:gravel":3148,"minecraft:white_tulip":62,"minecraft:crimson_fungus":273,"minecraft:blackstone":339,"minecraft:mangrove_roots":2,"minecraft:diorite_stairs":13,"minecraft:black_terracotta":26,"minecraft:fern":59,"minecraft:diamond_shovel":10,"minecraft:honey_bottle":1,"minecraft:carrot":409,"minecraft:chainmail_chestplate":4,"minecraft:chiseled_stone_bricks":3,"minecraft:poppy":12022,"minecraft:shulker_shell":290,"minecraft:rabbit_hide":1,"minecraft:oak_fence_gate":23,"minecraft:gunpowder":23688,"minecraft:birch_trapdoor":1,"minecraft:skeleton_skull":124,"minecraft:melon_seeds":33,"minecraft:lingering_potion":2,"minecraft:glowstone":222,"minecraft:chainmail_boots":4,"minecraft:azalea":67,"minecraft:chest":195,"minecraft:spruce_wood":11,"minecraft:cyan_concrete":10,"minecraft:spire_armor_trim_smithing_template":2,"minecraft:basalt":1,"minecraft:arrow":12296,"minecraft:powered_rail":12238,"minecraft:prismarine_bricks":5,"minecraft:quartz":664,"minecraft:written_book":16,"minecraft:oak_leaves":5,"minecraft:netherrack":10075,"minecraft:torchflower":1,"minecraft:firework_rocket":13953,"minecraft:water_bucket":45,"minecraft:purple_terracotta":4,"minecraft:stripped_spruce_log":57,"minecraft:oak_slab":1103,"minecraft:magenta_carpet":1,"minecraft:mossy_cobblestone":3,"minecraft:smithing_table":66,"minecraft:minecart":53,"minecraft:cyan_dye":1,"minecraft:diamond_leggings":4,"minecraft:poisonous_potato":3,"minecraft:lead":20,"minecraft:spectral_arrow":47,"minecraft:observer":126,"minecraft:dark_oak_pressure_plate":1,"minecraft:hopper_minecart":8,"minecraft:light_blue_concrete_powder":10133,"minecraft:copper_ingot":10304,"minecraft:chiseled_bookshelf":192,"minecraft:ominous_trial_key":1,"minecraft:grass_block":83,"minecraft:stick":3571,"minecraft:deepslate_brick_stairs":1,"minecraft:blue_dye":238,"minecraft:diorite":157,"minecraft:nether_gold_ore":78,"minecraft:light_blue_stained_glass":1,"minecraft:brewing_stand":1,"minecraft:torch":1345,"minecraft:sculk_catalyst":8,"minecraft:smooth_quartz":1,"minecraft:brown_wool":6,"minecraft:map":871,"minecraft:iron_leggings":18,"minecraft:smooth_quartz_slab":20,"minecraft:flowering_azalea":105,"minecraft:iron_axe":18,"minecraft:pink_petals":46,"minecraft:bucket":19,"minecraft:music_disc_cat":2,"minecraft:lapis_block":66,"minecraft:dandelion":507,"minecraft:smooth_basalt":78,"minecraft:redstone":1724,"minecraft:anvil":3676,"minecraft:brown_dye":64,"minecraft:warped_nylium":781,"minecraft:ender_chest":139,"minecraft:nether_wart":108,"minecraft:coarse_dirt":3,"minecraft:chiseled_quartz_block":5,"minecraft:raw_copper":12357,"minecraft:tuff":206,"minecraft:raw_iron":2106,"minecraft:composter":31,"minecraft:wither_skeleton_skull":2,"minecraft:light_gray_wool":13,"minecraft:smoker":1,"minecraft:iron_hoe":3,"minecraft:ender_eye":1,"minecraft:glass_pane":1,"minecraft:acacia_leaves":1,"minecraft:red_terracotta":16,"minecraft:filled_map":130,"minecraft:snow":66,"minecraft:shield":10,"minecraft:dead_horn_coral_fan":6,"minecraft:black_concrete_powder":57,"minecraft:diamond_chestplate":7,"minecraft:orange_terracotta":20,"minecraft:dragon_egg":5,"minecraft:iron_chestplate":8,"minecraft:quartz_stairs":5,"minecraft:cake":4,"minecraft:mossy_stone_bricks":47,"minecraft:blue_ice":243,"minecraft:oak_boat":9,"minecraft:waxed_oxidized_cut_copper":4,"minecraft:golden_sword":23,"minecraft:dead_fire_coral_fan":4,"minecraft:stripped_warped_stem":1,"minecraft:diamond_boots":3,"minecraft:slime_ball":3626,"minecraft:stripped_acacia_log":1,"minecraft:stripped_crimson_hyphae":2,"minecraft:beacon":4,"minecraft:stone_pickaxe":4,"minecraft:raw_gold":783,"minecraft:nether_quartz_ore":65,"minecraft:calcite":16,"minecraft:white_stained_glass":44,"minecraft:light_blue_shulker_box":1,"minecraft:glow_squid_spawn_egg":1},"minecraft:mined":{"minecraft:dragon_wall_head":2,"minecraft:blue_carpet":3,"minecraft:red_shulker_box":25,"minecraft:white_bed":14,"minecraft:granite":497,"minecraft:oak_wall_sign":5,"minecraft:nether_wart":1915,"minecraft:spawner":3,"minecraft:chorus_flower":12,"minecraft:polished_blackstone_bricks":7,"minecraft:magma_block":1066,"minecraft:cobbled_deepslate":37,"minecraft:barrel":158,"minecraft:fire":234,"minecraft:deepslate_lapis_ore":63,"minecraft:twisting_vines":20,"minecraft:light_gray_concrete":3,"minecraft:white_shulker_box":4,"minecraft:white_banner":11,"minecraft:tripwire":4,"minecraft:sandstone_slab":3,"minecraft:kelp_plant":226,"minecraft:crimson_nylium":71,"minecraft:smoker":1,"minecraft:powder_snow":2,"minecraft:torch":333,"minecraft:note_block":8,"minecraft:melon":720,"minecraft:white_stained_glass_pane":4,"minecraft:dead_bush":5,"minecraft:smooth_quartz_slab":24,"minecraft:sugar_cane":12,"minecraft:amethyst_block":120,"minecraft:birch_sapling":1,"minecraft:white_terracotta":2,"minecraft:repeater":29,"minecraft:wither_rose":5,"minecraft:birch_button":1,"minecraft:smooth_quartz":12,"minecraft:smooth_basalt":3,"minecraft:deepslate":7660,"minecraft:mossy_cobblestone":5,"minecraft:dark_oak_log":20,"minecraft:sea_lantern":2,"minecraft:end_stone":151349,"minecraft:dark_oak_fence":28,"minecraft:spruce_fence":5,"minecraft:redstone_wire":173,"minecraft:red_mushroom":32,"minecraft:redstone_ore":37,"minecraft:light_blue_concrete_powder":173,"minecraft:pink_concrete":6,"minecraft:andesite":3541,"minecraft:mossy_stone_brick_stairs":6,"minecraft:rail":20,"minecraft:ender_chest":69,"minecraft:birch_stairs":1,"minecraft:oak_slab":7,"minecraft:redstone_block":14,"minecraft:glass_pane":1,"minecraft:soul_sand":117,"minecraft:dandelion":71,"minecraft:cornflower":6,"minecraft:warped_roots":26,"minecraft:campfire":13,"minecraft:copper_ore":3623,"minecraft:tall_grass":175,"minecraft:purpur_pillar":391,"minecraft:deepslate_gold_ore":98,"minecraft:diorite":428,"minecraft:warped_wart_block":10,"minecraft:black_stained_glass":1,"minecraft:red_terracotta":16,"minecraft:coarse_dirt":1,"minecraft:cobblestone_wall":4,"minecraft:sunflower":1,"minecraft:gravel":147,"minecraft:cobweb":41,"minecraft:birch_sign":6,"minecraft:oak_button":2,"minecraft:stone_bricks":71,"minecraft:gold_ore":42,"minecraft:chipped_anvil":309,"minecraft:iron_trapdoor":119,"minecraft:fern":42,"minecraft:oak_sapling":1,"minecraft:mossy_stone_brick_slab":6,"minecraft:brewing_stand":2,"minecraft:budding_amethyst":14,"minecraft:cracked_polished_blackstone_bricks":4,"minecraft:frosted_ice":62,"minecraft:composter":8,"minecraft:gilded_blackstone":69,"minecraft:sculk_catalyst":3,"minecraft:turtle_egg":3,"minecraft:pointed_dripstone":11,"minecraft:flowering_azalea_leaves":1,"minecraft:iron_bars":42,"minecraft:azalea":29,"minecraft:spruce_slab":70,"minecraft:netherite_block":1,"minecraft:deepslate_redstone_ore":124,"minecraft:quartz_block":62,"minecraft:polished_blackstone_wall":1,"minecraft:medium_amethyst_bud":1,"minecraft:orange_terracotta":19,"minecraft:purpur_stairs":527,"minecraft:end_stone_brick_slab":714,"minecraft:beacon":27,"minecraft:nether_quartz_ore":538,"minecraft:wither_skeleton_wall_skull":1,"minecraft:oak_planks":90,"minecraft:wall_torch":133,"minecraft:cauldron":11,"minecraft:warped_nylium":1238,"minecraft:blue_terracotta":33,"minecraft:powered_rail":11,"minecraft:dark_oak_slab":4,"minecraft:blue_ice":56,"minecraft:tnt":80,"minecraft:smooth_stone_slab":9,"minecraft:oak_log":318,"minecraft:beetroots":7,"minecraft:dirt":18046,"minecraft:raw_copper_block":1,"minecraft:dispenser":4,"minecraft:ancient_debris":32,"minecraft:daylight_detector":5,"minecraft:crying_obsidian":4,"minecraft:quartz_stairs":22,"minecraft:mangrove_roots":2,"minecraft:mangrove_wall_sign":1,"minecraft:glow_lichen":64,"minecraft:lever":26,"minecraft:ladder":46,"minecraft:stone_button":2,"minecraft:decorated_pot":58,"minecraft:brown_mushroom_block":1,"minecraft:spruce_leaves":52,"minecraft:crimson_stem":126,"minecraft:hay_block":46,"minecraft:nether_sprouts":16,"minecraft:detector_rail":1,"minecraft:gold_block":36,"minecraft:bookshelf":161,"minecraft:shroomlight":23,"minecraft:deepslate_iron_ore":92,"minecraft:stripped_oak_log":13,"minecraft:wet_sponge":8,"minecraft:scaffolding":332,"minecraft:magenta_stained_glass":110,"minecraft:snow_block":165,"minecraft:basalt":4,"minecraft:oak_fence":53,"minecraft:stone_slab":3,"minecraft:deepslate_coal_ore":13,"minecraft:quartz_bricks":3,"minecraft:polished_blackstone_brick_stairs":1,"minecraft:birch_planks":109,"minecraft:sea_pickle":2,"minecraft:ice":563,"minecraft:white_wall_banner":18,"minecraft:bee_nest":6,"minecraft:cocoa":270,"minecraft:flower_pot":1,"minecraft:cracked_stone_bricks":18,"minecraft:mossy_stone_bricks":27,"minecraft:stripped_warped_stem":1,"minecraft:light_blue_concrete":376,"minecraft:jungle_leaves":2,"minecraft:obsidian":9535,"minecraft:chiseled_polished_blackstone":1,"minecraft:stone_brick_wall":1,"minecraft:jungle_log":43,"minecraft:oxeye_daisy":7,"minecraft:coal_block":3,"minecraft:hopper":71,"minecraft:crimson_fungus":3,"minecraft:diorite_stairs":4,"minecraft:purpur_slab":80,"minecraft:chiseled_tuff_bricks":2,"minecraft:weeping_vines_plant":18,"minecraft:tall_seagrass":10,"minecraft:sticky_piston":23,"minecraft:dead_fire_coral_wall_fan":1,"minecraft:moss_carpet":56,"minecraft:pumpkin":225,"minecraft:oak_sign":5,"minecraft:dirt_path":128,"minecraft:cave_vines":29,"minecraft:oak_stairs":110,"minecraft:quartz_slab":341,"minecraft:iron_block":160,"minecraft:piston_head":3,"minecraft:brown_mushroom":56,"minecraft:red_bed":14,"minecraft:soul_fire":4,"minecraft:amethyst_cluster":4,"minecraft:blast_furnace":3,"minecraft:polished_diorite_slab":14,"minecraft:glass":115,"minecraft:damaged_anvil":29,"minecraft:polished_diorite_stairs":18,"minecraft:light_gray_stained_glass":23,"minecraft:wheat":2212,"minecraft:lilac":19,"minecraft:waxed_copper_block":3,"minecraft:pumpkin_stem":1,"minecraft:lime_concrete":25,"minecraft:warped_fungus":3,"minecraft:stone_brick_stairs":31,"minecraft:copper_block":1,"minecraft:oak_fence_gate":4,"minecraft:red_mushroom_block":57,"minecraft:stonecutter":2,"minecraft:piston":32,"minecraft:pink_shulker_box":10,"minecraft:jack_o_lantern":7,"minecraft:shulker_box":417,"minecraft:nether_bricks":30,"minecraft:crimson_roots":52,"minecraft:moss_block":553,"minecraft:kelp":12,"minecraft:waxed_copper_grate":2,"minecraft:snow":9196,"minecraft:diamond_block":176,"minecraft:white_glazed_terracotta":1,"minecraft:potatoes":1158,"minecraft:magenta_concrete_powder":6,"minecraft:warped_stem":150,"minecraft:smooth_quartz_stairs":31,"minecraft:bamboo_sapling":2,"minecraft:bamboo":370,"minecraft:white_wool":7,"minecraft:cake":6,"minecraft:smithing_table":4,"minecraft:gray_concrete":2,"minecraft:comparator":10,"minecraft:stone_brick_slab":36,"minecraft:pink_concrete_powder":3,"minecraft:observer":36,"minecraft:short_grass":856,"minecraft:sponge":13,"minecraft:dropper":8,"minecraft:prismarine_brick_slab":6,"minecraft:white_carpet":14,"minecraft:spruce_log":479,"minecraft:birch_leaves":10,"minecraft:quartz_pillar":20,"minecraft:dripstone_block":138,"minecraft:spruce_fence_gate":2,"minecraft:black_shulker_box":6,"minecraft:spruce_planks":27,"minecraft:attached_melon_stem":4,"minecraft:sculk_vein":1,"minecraft:cobblestone_stairs":2,"minecraft:cave_vines_plant":18,"minecraft:grass_block":10713,"minecraft:soul_soil":23,"minecraft:stripped_warped_hyphae":56,"minecraft:tuff_bricks":9,"minecraft:smooth_stone":456,"minecraft:glowstone":221,"minecraft:iron_ore":527,"minecraft:target":3,"minecraft:anvil":17,"minecraft:azure_bluet":5,"minecraft:dark_oak_stairs":8,"minecraft:black_candle":4,"minecraft:birch_wall_sign":9,"minecraft:end_stone_bricks":523,"minecraft:blackstone":49,"minecraft:twisting_vines_plant":22,"minecraft:melon_stem":2,"minecraft:clay":72,"minecraft:calcite":3,"minecraft:poppy":11,"minecraft:chest":59,"minecraft:mushroom_stem":27,"minecraft:honeycomb_block":4,"minecraft:cobblestone":3649,"minecraft:slime_block":30,"minecraft:deepslate_copper_ore":253,"minecraft:pink_petals":2,"minecraft:seagrass":11,"minecraft:nether_wart_block":8,"minecraft:birch_trapdoor":4,"minecraft:birch_log":896,"minecraft:activator_rail":1,"minecraft:purpur_block":1259,"minecraft:waxed_oxidized_copper":1,"minecraft:diorite_wall":5,"minecraft:sand":300,"minecraft:netherrack":17427,"minecraft:oak_leaves":280,"minecraft:emerald_block":1020,"minecraft:redstone_lamp":11,"minecraft:nether_gold_ore":154,"minecraft:diamond_ore":640,"minecraft:tuff":636,"minecraft:red_carpet":4,"minecraft:deepslate_diamond_ore":734,"minecraft:candle":6,"minecraft:oak_door":5,"minecraft:brick_stairs":5,"minecraft:heavy_core":1,"minecraft:weeping_vines":13,"minecraft:light_blue_glazed_terracotta":2,"minecraft:white_stained_glass":203,"minecraft:polished_andesite_slab":1,"minecraft:mangrove_propagule":2,"minecraft:large_fern":78,"minecraft:spore_blossom":1,"minecraft:diorite_slab":2,"minecraft:oak_trapdoor":6,"minecraft:spruce_sapling":1,"minecraft:furnace":26,"minecraft:carrots":1520,"minecraft:stripped_spruce_log":1,"minecraft:black_concrete":4,"minecraft:bell":1,"minecraft:lantern":12,"minecraft:packed_ice":7544,"minecraft:chorus_plant":20,"minecraft:stone":13152,"minecraft:birch_pressure_plate":1,"minecraft:redstone_wall_torch":6,"minecraft:podzol":7,"minecraft:light_blue_shulker_box":6,"minecraft:flowering_azalea":14,"minecraft:infested_stone_bricks":1,"minecraft:crafting_table":32,"minecraft:lime_concrete_powder":7,"minecraft:lectern":18,"minecraft:lapis_ore":99,"minecraft:lily_pad":1,"minecraft:sculk":2,"minecraft:blue_bed":1,"minecraft:spruce_stairs":35,"minecraft:gray_wool":1,"minecraft:cactus":5,"minecraft:redstone_torch":6,"minecraft:sweet_berry_bush":172,"minecraft:yellow_bed":3,"minecraft:coal_ore":1476,"minecraft:end_rod":65,"minecraft:lodestone":1,"minecraft:terracotta":160,"minecraft:crimson_wall_sign":1,"minecraft:birch_fence":8,"minecraft:warped_slab":3},"minecraft:killed_by":{"minecraft:zombie":8,"minecraft:wolf":2,"minecraft:warden":5,"minecraft:wither":2,"minecraft:drowned":1,"minecraft:skeleton":5,"minecraft:pillager":1,"minecraft:bogged":1,"minecraft:stray":1,"minecraft:ender_dragon":5,"minecraft:slime":2,"minecraft:creeper":3,"minecraft:piglin":4,"minecraft:endermite":1,"minecraft:player":380,"minecraft:spider":4,"minecraft:enderman":6,"minecraft:iron_golem":32,"minecraft:hoglin":2,"minecraft:phantom":2},"minecraft:crafted":{"minecraft:black_dye":2,"minecraft:diamond_shovel":15,"minecraft:shulker_box":226,"minecraft:diamond_helmet":6,"minecraft:dried_kelp_block":1,"minecraft:golden_axe":1,"minecraft:smithing_table":1,"minecraft:golden_pickaxe":1,"minecraft:end_stone_brick_slab":2,"minecraft:stone_brick_stairs":1,"minecraft:golden_leggings":2,"minecraft:iron_pickaxe":3,"minecraft:netherite_ingot":7,"minecraft:iron_nugget":5465,"minecraft:diamond_hoe":2,"minecraft:wind_charge":300,"minecraft:spruce_fence":18,"minecraft:spruce_stairs":28,"minecraft:enchanted_book":6,"minecraft:oak_fence_gate":2,"minecraft:birch_trapdoor":4,"minecraft:writable_book":1,"minecraft:armor_stand":8,"minecraft:iron_shovel":2,"minecraft:barrel":274,"minecraft:stone":68,"minecraft:warped_planks":244,"minecraft:bow":5,"minecraft:chest":249,"minecraft:netherite_helmet":1,"minecraft:oak_button":4,"minecraft:yellow_terracotta":8,"minecraft:copper_block":25,"minecraft:rail":16,"minecraft:bricks":1,"minecraft:birch_button":7,"minecraft:stone_bricks":12,"minecraft:golden_boots":2,"minecraft:white_banner":1,"minecraft:cauldron":8,"minecraft:iron_helmet":14,"minecraft:tnt":166,"minecraft:purple_dye":8,"minecraft:yellow_dye":1226,"minecraft:stick":8802,"minecraft:iron_ingot":4424,"minecraft:blue_terracotta":12800,"minecraft:golden_chestplate":2,"minecraft:spruce_button":1,"minecraft:furnace":149,"minecraft:blast_furnace":3,"minecraft:mushroom_stew":2,"minecraft:raw_copper_block":64,"minecraft:oak_trapdoor":6,"minecraft:flint_and_steel":4,"minecraft:scaffolding":1710,"minecraft:netherite_chestplate":1,"minecraft:iron_trapdoor":169,"minecraft:iron_sword":5,"minecraft:jungle_planks":56,"minecraft:anvil":7,"minecraft:stonecutter":1,"minecraft:torch":196,"minecraft:diamond_chestplate":4,"minecraft:smooth_stone":63,"minecraft:oak_pressure_plate":64,"minecraft:birch_slab":114,"minecraft:slime_block":617,"minecraft:lever":7,"minecraft:bookshelf":1,"minecraft:iron_bars":16,"minecraft:mace":1,"minecraft:quartz_block":86,"minecraft:glass":97,"minecraft:diamond_leggings":5,"minecraft:netherite_boots":1,"minecraft:melon_seeds":3053,"minecraft:magenta_dye":38,"minecraft:glass_bottle":984,"minecraft:deepslate":1,"minecraft:emerald":1743,"minecraft:diamond_axe":2,"minecraft:spruce_door":3,"minecraft:copper_ingot":695,"minecraft:oak_wood":3,"minecraft:green_terracotta":8,"minecraft:iron_block":1240,"minecraft:gold_ingot":1511,"minecraft:light_gray_dye":293,"minecraft:packed_ice":30,"minecraft:smooth_stone_slab":912,"minecraft:bone_meal":22603,"minecraft:diamond":537,"minecraft:ladder":3,"minecraft:spruce_slab":132,"minecraft:diamond_boots":5,"minecraft:redstone_block":71,"minecraft:dark_oak_planks":32,"minecraft:golden_helmet":3,"minecraft:wheat":342,"minecraft:coal_block":12,"minecraft:daylight_detector":2,"minecraft:crossbow":6,"minecraft:dried_kelp":192,"minecraft:red_bed":1,"minecraft:glowstone":5,"minecraft:golden_apple":117,"minecraft:oak_stairs":20,"minecraft:iron_leggings":16,"minecraft:white_bed":21,"minecraft:oak_planks":5955,"minecraft:warped_hyphae":66,"minecraft:hopper":2,"minecraft:iron_boots":15,"minecraft:raw_copper":1151,"minecraft:netherite_upgrade_smithing_template":218,"minecraft:honeycomb_block":4,"minecraft:raw_iron_block":39,"minecraft:item_frame":6,"minecraft:oak_slab":816,"minecraft:crafting_table":47,"minecraft:spruce_planks":1752,"minecraft:baked_potato":353,"minecraft:gold_block":125,"minecraft:birch_planks":2980,"minecraft:pumpkin_seeds":76,"minecraft:iron_chestplate":7,"minecraft:book":36,"minecraft:paper":12510,"minecraft:charcoal":1,"minecraft:diamond_pickaxe":2,"minecraft:emerald_block":811,"minecraft:shield":3,"minecraft:snow_block":393,"minecraft:redstone_torch":1,"minecraft:shears":5,"minecraft:cookie":96,"minecraft:raw_iron":916,"minecraft:redstone":1653,"minecraft:light_gray_stained_glass":488,"minecraft:stone_button":2,"minecraft:dark_oak_trapdoor":2,"minecraft:end_stone_bricks":1,"minecraft:diamond_block":59,"minecraft:blue_ice":764,"minecraft:netherite_leggings":3,"minecraft:leather":1,"minecraft:black_terracotta":16,"minecraft:iron_axe":4,"minecraft:iron_hoe":2,"minecraft:filled_map":28,"minecraft:netherite_scrap":3,"minecraft:minecart":3,"minecraft:cooked_beef":9,"minecraft:sugar":320,"minecraft:red_dye":1,"minecraft:bone_block":244,"minecraft:crimson_planks":460,"minecraft:diamond_sword":4,"minecraft:bucket":8,"minecraft:air":0,"minecraft:bread":288,"minecraft:blue_dye":1824,"minecraft:oak_boat":4,"minecraft:white_wool":124,"minecraft:gold_nugget":1,"minecraft:raw_gold":567,"minecraft:lapis_lazuli":2232,"minecraft:lapis_block":292,"minecraft:clay":1832,"minecraft:firework_rocket":13470},"minecraft:custom":{"minecraft:interact_with_crafting_table":1037,"minecraft:damage_blocked_by_shield":21267,"minecraft:play_time":38928662,"minecraft:deaths":1027,"minecraft:jump":347150,"minecraft:play_record":13,"minecraft:interact_with_cartography_table":1,"minecraft:interact_with_smoker":6,"minecraft:inspect_dispenser":199,"minecraft:horse_one_cm":257908,"minecraft:inspect_dropper":200,"minecraft:interact_with_anvil":387,"minecraft:inspect_hopper":2841,"minecraft:tune_noteblock":1610,"minecraft:time_since_rest":1667,"minecraft:swim_one_cm":1135265,"minecraft:open_chest":9069,"minecraft:open_shulker_box":1961,"minecraft:clean_banner":16,"minecraft:damage_resisted":347506,"minecraft:play_noteblock":22,"minecraft:talked_to_villager":260,"minecraft:interact_with_brewingstand":19,"minecraft:interact_with_beacon":41,"minecraft:fill_cauldron":67,"minecraft:interact_with_campfire":491,"minecraft:damage_dealt_resisted":160395,"minecraft:boat_one_cm":1136042,"minecraft:damage_taken":5921743,"minecraft:aviate_one_cm":266236059,"minecraft:open_barrel":1048,"minecraft:bell_ring":357,"minecraft:leave_game":869,"minecraft:time_since_death":1639,"minecraft:eat_cake_slice":37,"minecraft:enchant_item":113,"minecraft:interact_with_furnace":501,"minecraft:traded_with_villager":84,"minecraft:sleep_in_bed":618,"minecraft:damage_dealt":1373501,"minecraft:use_cauldron":48,"minecraft:interact_with_smithing_table":53,"minecraft:damage_dealt_absorbed":10143,"minecraft:target_hit":23,"minecraft:sneak_time":1642680,"minecraft:interact_with_blast_furnace":11,"minecraft:total_world_time":38928662,"minecraft:interact_with_stonecutter":32,"minecraft:fly_one_cm":136250669,"minecraft:fish_caught":19,"minecraft:fall_one_cm":14222644,"minecraft:sprint_one_cm":36487156,"minecraft:drop":30735,"minecraft:walk_on_water_one_cm":1987251,"minecraft:interact_with_loom":6,"minecraft:open_enderchest":592,"minecraft:player_kills":486,"minecraft:crouch_one_cm":6574674,"minecraft:mob_kills":35210,"minecraft:climb_one_cm":908413,"minecraft:walk_one_cm":46286171,"minecraft:walk_under_water_one_cm":2462791,"minecraft:raid_trigger":7,"minecraft:interact_with_grindstone":30,"minecraft:damage_absorbed":4198,"minecraft:trigger_trapped_chest":20,"minecraft:minecart_one_cm":727569},"minecraft:picked_up":{"minecraft:red_sandstone_stairs":3,"minecraft:smithing_table":4,"minecraft:lead":43,"minecraft:stone_slab":3,"minecraft:enchanted_book":231,"minecraft:music_disc_cat":9,"minecraft:string":12532,"minecraft:dark_oak_pressure_plate":1,"minecraft:wayfinder_armor_trim_smithing_template":1,"minecraft:pufferfish":5,"minecraft:shroomlight":13,"minecraft:diamond_leggings":2,"minecraft:dead_bubble_coral_fan":1,"minecraft:trial_key":8,"minecraft:warped_slab":2,"minecraft:hopper_minecart":15,"minecraft:crimson_sign":1,"minecraft:diamond_ore":371,"minecraft:bamboo_chest_raft":93,"minecraft:purpur_pillar":249,"minecraft:golden_axe":2,"minecraft:honeycomb_block":4,"minecraft:golden_chestplate":3,"minecraft:cauldron":14,"minecraft:pink_terracotta":418,"minecraft:honey_bottle":3,"minecraft:vex_armor_trim_smithing_template":1,"minecraft:glowstone":152,"minecraft:end_rod":32,"minecraft:white_terracotta":2,"minecraft:blaze_rod":3,"minecraft:iron_bars":99,"minecraft:snowball":976,"minecraft:sponge":716,"minecraft:barrier":1,"minecraft:dune_armor_trim_smithing_template":1,"minecraft:feather":155,"minecraft:cooked_beef":225,"minecraft:water_bucket":32,"minecraft:brown_wool":6,"minecraft:copper_block":1,"minecraft:flint":5418,"minecraft:cherry_fence":2,"minecraft:pink_concrete_powder":70,"minecraft:lantern":41,"minecraft:stonecutter":3,"minecraft:guster_banner_pattern":2,"minecraft:diamond_helmet":2,"minecraft:birch_hanging_sign":1,"minecraft:rabbit":8,"minecraft:glow_lichen":64,"minecraft:stripped_crimson_stem":1,"minecraft:stripped_spruce_log":2,"minecraft:brown_mushroom_block":1,"minecraft:dead_fire_coral_fan":2,"minecraft:netherite_block":2,"minecraft:snout_armor_trim_smithing_template":2,"minecraft:blue_terracotta":7124,"minecraft:deepslate":558,"minecraft:angler_pottery_sherd":1,"minecraft:lever":98,"minecraft:cherry_hanging_sign":1,"minecraft:granite":576,"minecraft:golden_horse_armor":3,"minecraft:deepslate_coal_ore":2,"minecraft:jack_o_lantern":454,"minecraft:light_gray_carpet":7,"minecraft:ominous_trial_key":7,"minecraft:crimson_roots":1830,"minecraft:diamond_pickaxe":31,"minecraft:bee_nest":1,"minecraft:ominous_bottle":8,"minecraft:stripped_warped_hyphae":56,"minecraft:clay_ball":654,"minecraft:leather_leggings":2,"minecraft:golden_pickaxe":4,"minecraft:redstone_lamp":2,"minecraft:dragon_head":2,"minecraft:purpur_block":507,"minecraft:cornflower":39,"minecraft:elytra":10,"minecraft:flint_and_steel":19,"minecraft:white_carpet":3530,"minecraft:white_stained_glass":20,"minecraft:glass_pane":1,"minecraft:netherite_sword":27,"minecraft:stripped_warped_stem":1,"minecraft:poppy":8784,"minecraft:spruce_slab":77,"minecraft:minecart":86,"minecraft:birch_sapling":398,"minecraft:piston":102,"minecraft:diamond_hoe":9,"minecraft:copper_ore":285,"minecraft:black_stained_glass":2,"minecraft:stone":3726,"minecraft:fire_charge":2,"minecraft:white_dye":19,"minecraft:flow_pottery_sherd":4,"minecraft:netherite_pickaxe":12,"minecraft:music_disc_creator_music_box":4,"minecraft:diamond_chestplate":4,"minecraft:decorated_pot":21,"minecraft:purpur_slab":64,"minecraft:hay_block":46,"minecraft:totem_of_undying":1,"minecraft:mutton":278,"minecraft:rail":14,"minecraft:bone_block":175,"minecraft:oxeye_daisy":147,"minecraft:clock":13,"minecraft:tripwire_hook":3,"minecraft:packed_mud":1,"minecraft:purpur_stairs":128,"minecraft:lily_pad":3,"minecraft:diorite_stairs":10,"minecraft:paper":5885,"minecraft:apple":115,"minecraft:wild_armor_trim_smithing_template":1,"minecraft:warped_stem":150,"minecraft:oak_fence_gate":14,"minecraft:stone_pickaxe":3,"minecraft:iron_ore":39,"minecraft:dark_oak_stairs":8,"minecraft:smooth_basalt":9,"minecraft:milk_bucket":1,"minecraft:light_gray_stained_glass":272,"minecraft:sweet_berries":2494,"minecraft:lime_concrete":468,"minecraft:crying_obsidian":3,"minecraft:dragon_egg":5,"minecraft:leather_helmet":3,"minecraft:oak_wood":124,"minecraft:diamond_shovel":9,"minecraft:coal_ore":120,"minecraft:slime_ball":4315,"minecraft:tide_armor_trim_smithing_template":1,"minecraft:short_grass":2,"minecraft:rib_armor_trim_smithing_template":1,"minecraft:birch_sign":29,"minecraft:dark_oak_hanging_sign":1,"minecraft:lodestone":1,"minecraft:baked_potato":236,"minecraft:smooth_quartz_slab":19,"minecraft:hopper":332,"minecraft:light_blue_concrete":5784,"minecraft:ender_chest":138,"minecraft:sentry_armor_trim_smithing_template":1,"minecraft:gilded_blackstone":62,"minecraft:stone_brick_stairs":36,"minecraft:lapis_block":2,"minecraft:deepslate_lapis_ore":3,"minecraft:experience_bottle":277,"minecraft:red_sand":89,"minecraft:smooth_stone":5301,"minecraft:comparator":72,"minecraft:bucket":11,"minecraft:eye_armor_trim_smithing_template":1,"minecraft:white_tulip":1,"minecraft:rose_bush":64,"minecraft:azalea":349,"minecraft:iron_pickaxe":5,"minecraft:smooth_quartz":1,"minecraft:smooth_quartz_stairs":32,"minecraft:deepslate_iron_ore":2,"minecraft:tipped_arrow":384,"minecraft:spruce_stairs":58,"minecraft:netherite_shovel":2,"minecraft:diorite":415,"minecraft:goat_horn":5,"minecraft:rotten_flesh":12895,"minecraft:mangrove_roots":2,"minecraft:deepslate_copper_ore":60,"minecraft:chorus_flower":12,"minecraft:obsidian":8703,"minecraft:cobblestone":67439,"minecraft:pink_petals":45,"minecraft:leather_chestplate":5,"minecraft:lilac":43,"minecraft:raiser_armor_trim_smithing_template":1,"minecraft:repeater":107,"minecraft:dead_tube_coral_fan":1,"minecraft:andesite":6450,"minecraft:golden_leggings":2,"minecraft:beacon":27,"minecraft:potato":5065,"minecraft:silence_armor_trim_smithing_template":1,"minecraft:dirt":27198,"minecraft:cut_sandstone_slab":122,"minecraft:name_tag":2,"minecraft:glass":2905,"minecraft:bone":4085,"minecraft:bow":114,"minecraft:wheat_seeds":6883,"minecraft:bolt_armor_trim_smithing_template":1,"minecraft:netherite_axe":19,"minecraft:mossy_stone_bricks":57,"minecraft:fletching_table":128,"minecraft:bamboo":4922,"minecraft:cyan_concrete":1,"minecraft:scrape_pottery_sherd":4,"minecraft:diorite_wall":6,"minecraft:light_blue_shulker_box":6,"minecraft:nether_brick_stairs":3,"minecraft:grass_block":57,"minecraft:diamond_block":881,"minecraft:spectral_arrow":8,"minecraft:mossy_cobblestone":5,"minecraft:sugar":21,"minecraft:slime_block":2671,"minecraft:netherite_helmet":3,"minecraft:soul_lantern":9,"minecraft:cracked_polished_blackstone_bricks":2,"minecraft:crossbow":25,"minecraft:breeze_rod":76,"minecraft:bone_meal":5404,"minecraft:golden_apple":123,"minecraft:emerald":426,"minecraft:piglin_banner_pattern":1,"minecraft:netherrack":13236,"minecraft:chorus_fruit":426,"minecraft:oak_leaves":110,"minecraft:waxed_oxidized_cut_copper":3,"minecraft:azure_bluet":115,"minecraft:ladder":155,"minecraft:brown_mushroom":59,"minecraft:packed_ice":13848,"minecraft:stone_brick_wall":3,"minecraft:diorite_slab":2,"minecraft:chain":17,"minecraft:shield":7,"minecraft:brick":112,"minecraft:oak_trapdoor":30,"minecraft:moss_carpet":1103,"minecraft:birch_fence":1,"minecraft:blackstone":181,"minecraft:spire_armor_trim_smithing_template":1,"minecraft:end_stone":338829,"minecraft:cherry_stairs":2,"minecraft:bamboo_hanging_sign":1,"minecraft:note_block":9,"minecraft:polished_blackstone_bricks":3,"minecraft:trident":11,"minecraft:purple_terracotta":1,"minecraft:weeping_vines":18,"minecraft:red_shulker_box":47,"minecraft:nether_bricks":6,"minecraft:pink_tulip":65,"minecraft:ward_armor_trim_smithing_template":1,"minecraft:brick_stairs":5,"minecraft:skeleton_skull":62,"minecraft:netherite_boots":6,"minecraft:basalt":1,"minecraft:golden_carrot":90,"minecraft:magenta_banner":6,"minecraft:leather":428,"minecraft:ice":318,"minecraft:bedrock":8,"minecraft:crimson_fungus":198,"minecraft:chainmail_chestplate":5,"minecraft:yellow_bed":2,"minecraft:cobblestone_wall":3,"minecraft:gunpowder":24371,"minecraft:orange_terracotta":19,"minecraft:cooked_mutton":303,"minecraft:red_carpet":370,"minecraft:coast_armor_trim_smithing_template":1,"minecraft:pearlescent_froglight":1,"minecraft:rabbit_hide":31,"minecraft:spruce_wood":1,"minecraft:iron_ingot":49040,"minecraft:cooked_chicken":35,"minecraft:jungle_hanging_sign":1,"minecraft:prismarine_brick_slab":6,"minecraft:polished_andesite_slab":3,"minecraft:sculk_catalyst":14,"minecraft:acacia_hanging_sign":1,"minecraft:nether_quartz_ore":67,"minecraft:warped_fungus":351,"minecraft:black_candle":4,"minecraft:emerald_block":1135,"minecraft:heavy_core":1,"minecraft:stone_brick_slab":21,"minecraft:quartz":1195,"minecraft:dandelion":426,"minecraft:lava_bucket":6,"minecraft:amethyst_shard":40,"minecraft:light_blue_concrete_powder":3315,"minecraft:pumpkin_seeds":4,"minecraft:chainmail_leggings":5,"minecraft:terracotta":17654,"minecraft:damaged_anvil":3,"minecraft:netherite_hoe":5,"minecraft:end_stone_brick_slab":1938,"minecraft:sunflower":1,"minecraft:wooden_axe":1,"minecraft:iron_chestplate":3,"minecraft:chainmail_boots":5,"minecraft:creeper_head":62,"minecraft:flower_pot":1,"minecraft:anvil":2648,"minecraft:prismarine_shard":46,"minecraft:diamond_sword":18,"minecraft:oak_stairs":111,"minecraft:wither_rose":7,"minecraft:birch_button":3,"minecraft:brewing_stand":3,"minecraft:golden_sword":19,"minecraft:amethyst_block":125,"minecraft:dark_oak_trapdoor":4,"minecraft:soul_soil":22,"minecraft:cooked_salmon":23,"minecraft:beetroot":126,"minecraft:gold_nugget":481,"minecraft:cobbled_deepslate":6497,"minecraft:spruce_planks":75,"minecraft:acacia_fence_gate":2,"minecraft:written_book":2,"minecraft:flower_banner_pattern":1,"minecraft:netherite_upgrade_smithing_template":2,"minecraft:enchanted_golden_apple":70,"minecraft:melon_slice":4897,"minecraft:coal_block":227,"minecraft:golden_helmet":2,"minecraft:white_glazed_terracotta":4,"minecraft:magenta_concrete_powder":56,"minecraft:composter":29,"minecraft:waxed_copper_grate":6,"minecraft:warped_planks":1,"minecraft:rabbit_foot":3,"minecraft:black_dye":2,"minecraft:shaper_armor_trim_smithing_template":1,"minecraft:light_blue_wool":12,"minecraft:tropical_fish":69,"minecraft:blue_dye":14,"minecraft:iron_block":399,"minecraft:netherite_chestplate":3,"minecraft:host_armor_trim_smithing_template":1,"minecraft:birch_log":819,"minecraft:magma_block":1095,"minecraft:polished_diorite_slab":2,"minecraft:birch_slab":18,"minecraft:jungle_log":52,"minecraft:smoker":1,"minecraft:netherite_leggings":4,"minecraft:map":55,"minecraft:disc_fragment_5":61,"minecraft:twisting_vines":71,"minecraft:chipped_anvil":3064,"minecraft:glowstone_dust":163,"minecraft:moss_block":2385,"minecraft:warped_wart_block":11,"minecraft:dropper":22,"minecraft:structure_void":1,"minecraft:ink_sac":67,"minecraft:dark_oak_log":20,"minecraft:red_terracotta":16,"minecraft:barrel":173,"minecraft:quartz_bricks":5,"minecraft:stripped_acacia_log":1,"minecraft:dispenser":4,"minecraft:black_concrete_powder":57,"minecraft:writable_book":4,"minecraft:blue_ice":126,"minecraft:chainmail_helmet":3,"minecraft:bread":38,"minecraft:cherry_slab":3,"minecraft:dark_oak_fence":28,"minecraft:spruce_leaves":1,"minecraft:crafting_table":37,"minecraft:coarse_dirt":2,"minecraft:sandstone_slab":4,"minecraft:nether_wart":5752,"minecraft:music_disc_creator":2,"minecraft:conduit":180,"minecraft:wind_charge":157,"minecraft:red_bed":14,"minecraft:flow_banner_pattern":1,"minecraft:netherite_scrap":29,"minecraft:cracked_stone_bricks":19,"minecraft:deepslate_diamond_ore":75,"minecraft:beef":179,"minecraft:iron_nugget":1159,"minecraft:guster_pottery_sherd":2,"minecraft:quartz_stairs":5,"minecraft:chest":318,"minecraft:raw_copper_block":8,"minecraft:egg":49,"minecraft:sandstone":1954,"minecraft:oak_door":6,"minecraft:glow_item_frame":1,"minecraft:cut_red_sandstone_slab":65,"minecraft:amethyst_cluster":4,"minecraft:spruce_fence":3,"minecraft:mace":6,"minecraft:carrot":5632,"minecraft:redstone":2390,"minecraft:prismarine_crystals":57,"minecraft:blue_carpet":3,"minecraft:tnt":201,"minecraft:cooked_cod":46,"minecraft:beetroot_seeds":4,"minecraft:peony":28,"minecraft:shears":8,"minecraft:diamond_boots":2,"minecraft:warped_sign":1,"minecraft:gold_ingot":384,"minecraft:flow_armor_trim_smithing_template":3,"minecraft:tuff_bricks":8,"minecraft:white_shulker_box":10,"minecraft:glow_berries":50,"minecraft:lime_concrete_powder":3263,"minecraft:white_wool":148,"minecraft:lapis_ore":3,"minecraft:stripped_oak_log":606,"minecraft:chiseled_bookshelf":128,"minecraft:red_mushroom_block":3,"minecraft:red_mushroom":95,"minecraft:ochre_froglight":5,"minecraft:filled_map":227,"minecraft:oak_log":3136,"minecraft:ancient_debris":98,"minecraft:golden_boots":4,"minecraft:white_banner":55,"minecraft:birch_pressure_plate":2,"minecraft:stone_bricks":147,"minecraft:kelp":1372,"minecraft:glass_bottle":15,"minecraft:iron_sword":7,"minecraft:flowering_azalea":269,"minecraft:white_stained_glass_pane":3,"minecraft:dark_oak_slab":4,"minecraft:daylight_detector":7,"minecraft:yellow_concrete":4,"minecraft:spyglass":14,"minecraft:light_blue_glazed_terracotta":31,"minecraft:gravel":1164,"minecraft:birch_stairs":5,"minecraft:spruce_sapling":341,"minecraft:spruce_log":542,"minecraft:firework_rocket":4820,"minecraft:bamboo_trapdoor":1,"minecraft:light_blue_carpet":2,"minecraft:diamond_axe":12,"minecraft:gray_wool":10,"minecraft:warped_roots":2511,"minecraft:oak_button":25,"minecraft:melon_seeds":22,"minecraft:warped_nylium":941,"minecraft:crimson_nylium":60,"minecraft:ender_pearl":36389,"minecraft:shulker_shell":629,"minecraft:wheat":2076,"minecraft:redstone_block":19,"minecraft:iron_trapdoor":425,"minecraft:dead_horn_coral_fan":1,"minecraft:potion":12,"minecraft:crimson_planks":1,"minecraft:raw_copper":30034,"minecraft:oak_hanging_sign":24,"minecraft:smooth_stone_slab":21,"minecraft:iron_leggings":1,"minecraft:armor_stand":4,"minecraft:sticky_piston":33,"minecraft:netherite_ingot":62,"minecraft:pink_shulker_box":19,"minecraft:oak_sign":15,"minecraft:sea_pickle":6,"minecraft:activator_rail":5,"minecraft:tnt_minecart":1,"minecraft:black_shulker_box":6,"minecraft:redstone_torch":51,"minecraft:calcite":16,"minecraft:iron_boots":1,"minecraft:furnace":159,"minecraft:stick":1041,"minecraft:oak_fence":51,"minecraft:torch":891,"minecraft:porkchop":315,"minecraft:snow_block":268,"minecraft:dried_kelp":55,"minecraft:target":1,"minecraft:dead_brain_coral_fan":1,"minecraft:pointed_dripstone":38,"minecraft:quartz_block":5548,"minecraft:nether_gold_ore":167,"minecraft:cactus":168,"minecraft:green_wool":22,"minecraft:spruce_hanging_sign":3,"minecraft:leather_horse_armor":1,"minecraft:suspicious_sand":1,"minecraft:cod":23,"minecraft:nautilus_shell":62,"minecraft:magma_cream":8,"minecraft:chiseled_quartz_block":4,"minecraft:tuff":565,"minecraft:light_gray_dye":17,"minecraft:wither_skeleton_skull":114,"minecraft:lapis_lazuli":3078,"minecraft:leather_boots":7,"minecraft:pink_banner":48,"minecraft:raw_gold":286,"minecraft:bell":3,"minecraft:light_blue_dye":220,"minecraft:powered_rail":2807,"minecraft:oak_planks":2947,"minecraft:mossy_stone_brick_stairs":6,"minecraft:ghast_tear":154,"minecraft:pink_concrete":653,"minecraft:black_terracotta":5,"minecraft:cooked_porkchop":582,"minecraft:music_disc_13":1,"minecraft:poisonous_potato":12,"minecraft:sand":50603,"minecraft:shulker_box":619,"minecraft:light_gray_concrete":40,"minecraft:spruce_fence_gate":2,"minecraft:clay":22452,"minecraft:diamond":3433,"minecraft:black_concrete":1886,"minecraft:white_concrete":1,"minecraft:oak_sapling":926,"minecraft:nether_star":7,"minecraft:end_stone_bricks":256,"minecraft:lingering_potion":3,"minecraft:fishing_rod":1,"minecraft:cocoa_beans":1107,"minecraft:charcoal":127,"minecraft:chicken":116,"minecraft:chest_minecart":1,"minecraft:wooden_pickaxe":3,"minecraft:cooked_rabbit":134,"minecraft:gold_block":90,"minecraft:mangrove_hanging_sign":2,"minecraft:diamond_horse_armor":2,"minecraft:iron_axe":13,"minecraft:item_frame":96,"minecraft:quartz_slab":56,"minecraft:candle":37,"minecraft:detector_rail":11,"minecraft:oak_boat":105,"minecraft:player_head":1,"minecraft:observer":39,"minecraft:light_gray_wool":50,"minecraft:lectern":21,"minecraft:sugar_cane":51643,"minecraft:spruce_trapdoor":5,"minecraft:phantom_membrane":48,"minecraft:stripped_crimson_hyphae":2,"minecraft:raw_iron":1600,"minecraft:copper_ingot":6982,"minecraft:bowl":2,"minecraft:gray_dye":1,"minecraft:quartz_pillar":51,"minecraft:stone_button":16,"minecraft:iron_horse_armor":1,"minecraft:cherry_fence_gate":1,"minecraft:arrow":13402,"minecraft:saddle":3,"minecraft:wet_sponge":7,"minecraft:glow_ink_sac":2,"minecraft:crimson_stem":140,"minecraft:salmon":27,"minecraft:birch_planks":466,"minecraft:mushroom_stew":2,"minecraft:waxed_copper_block":7,"minecraft:nether_wart_block":126,"minecraft:cobblestone_stairs":2,"minecraft:smooth_sandstone":63,"minecraft:heart_of_the_sea":2,"minecraft:soul_sand":230,"minecraft:book":1065,"minecraft:scaffolding":2121,"minecraft:oak_slab":1097,"minecraft:pumpkin":225,"minecraft:brush":2,"minecraft:raw_iron_block":13,"minecraft:dripstone_block":125,"minecraft:blast_furnace":3,"minecraft:white_bed":15,"minecraft:mossy_stone_brick_slab":4,"minecraft:spider_eye":1344,"minecraft:campfire":2,"minecraft:honey_block":16,"minecraft:iron_helmet":2,"minecraft:black_wool":17,"minecraft:magenta_concrete":139,"minecraft:coal":3480,"minecraft:chiseled_tuff_bricks":3},"minecraft:used":{"minecraft:moss_block":1286,"minecraft:tuff_bricks":8,"minecraft:writable_book":14,"minecraft:jack_o_lantern":102,"minecraft:heavy_core":1,"minecraft:smooth_quartz_slab":17,"minecraft:dispenser":56,"minecraft:poppy":108,"minecraft:stone":36494,"minecraft:quartz_stairs":61,"minecraft:warped_sign":1,"minecraft:rotten_flesh":175,"minecraft:soul_sand":312,"minecraft:cocoa_beans":360,"minecraft:crafter":7,"minecraft:deepslate_brick_slab":8,"minecraft:snowball":28,"minecraft:azure_bluet":65,"minecraft:packed_ice":17832,"minecraft:lava_bucket":1155,"minecraft:quartz_pillar":111,"minecraft:villager_spawn_egg":242,"minecraft:deepslate_copper_ore":35,"minecraft:quartz_block":3653,"minecraft:netherite_hoe":605,"minecraft:netherite_boots":6,"minecraft:bow":2745,"minecraft:ominous_bottle":6,"minecraft:oak_sapling":514,"minecraft:cooked_cod":27,"minecraft:mossy_stone_bricks":10,"minecraft:bamboo_mosaic":1,"minecraft:damaged_anvil":1,"minecraft:chorus_fruit":320,"minecraft:prismarine":2,"minecraft:blackstone":40,"minecraft:cactus":4,"minecraft:composter":80,"minecraft:clay":10132,"minecraft:golden_apple":45,"minecraft:glow_berries":96,"minecraft:blast_furnace":3,"minecraft:acacia_leaves":64,"minecraft:gray_concrete":2384,"minecraft:purple_terracotta":1482,"minecraft:bamboo_button":1,"minecraft:birch_fence":1424,"minecraft:birch_slab":76,"minecraft:deepslate_iron_ore":1,"minecraft:white_glazed_terracotta":43,"minecraft:oak_pressure_plate":10,"minecraft:coal_block":2,"minecraft:nether_wart_block":14,"minecraft:diamond_sword":119,"minecraft:smithing_table":5,"minecraft:birch_log":25,"minecraft:oak_boat":120,"minecraft:compass":2,"minecraft:diorite_slab":9,"minecraft:diorite_stairs":14,"minecraft:oak_trapdoor":599,"minecraft:orange_concrete":609,"minecraft:carved_pumpkin":35,"minecraft:armor_stand":21,"minecraft:light_gray_carpet":23,"minecraft:tinted_glass":13,"minecraft:jungle_hanging_sign":2,"minecraft:torch":1596,"minecraft:cooked_salmon":23,"minecraft:structure_block":14,"minecraft:orange_stained_glass":1,"minecraft:brewing_stand":2,"minecraft:nether_quartz_ore":1,"minecraft:oak_fence_gate":199,"minecraft:fern":2,"minecraft:sea_lantern":100,"minecraft:iron_block":2368,"minecraft:cherry_slab":1,"minecraft:bamboo_hanging_sign":1,"minecraft:jungle_log":110,"minecraft:barrel":328,"minecraft:bamboo":543,"minecraft:flow_pottery_sherd":2,"minecraft:diamond_chestplate":1,"minecraft:lime_concrete":34,"minecraft:magenta_terracotta":206,"minecraft:trapped_chest":4,"minecraft:acacia_planks":100,"minecraft:cherry_log":2,"minecraft:wheat_seeds":2192,"minecraft:light_blue_shulker_box":5,"minecraft:birch_planks":5287,"minecraft:cherry_planks":1,"minecraft:cauldron":11,"minecraft:spruce_fence_gate":40,"minecraft:leather_boots":2,"minecraft:glow_ink_sac":4,"minecraft:bamboo_mosaic_stairs":1,"minecraft:diamond_block":1,"minecraft:rail":81,"minecraft:acacia_hanging_sign":1,"minecraft:red_bed":22,"minecraft:white_bed":222,"minecraft:campfire":32,"minecraft:endermite_spawn_egg":2,"minecraft:spruce_log":291,"minecraft:mushroom_stem":10740,"minecraft:diamond_pickaxe":198324,"minecraft:ominous_trial_key":6,"minecraft:diamond_shovel":23790,"minecraft:wind_charge":383,"minecraft:oak_button":75,"minecraft:tnt_minecart":311,"minecraft:magenta_concrete_powder":116,"minecraft:spruce_trapdoor":13,"minecraft:bamboo_slab":4,"minecraft:spruce_sapling":103,"minecraft:potion":9,"minecraft:cooked_porkchop":674,"minecraft:porkchop":30,"minecraft:stripped_oak_log":488,"minecraft:brush":5,"minecraft:dandelion":77,"minecraft:diamond_leggings":1,"minecraft:moss_carpet":11,"minecraft:blue_terracotta":15299,"minecraft:decorated_pot":20,"minecraft:nether_wart":1919,"minecraft:green_terracotta":190,"minecraft:soul_campfire":11,"minecraft:spruce_leaves":2168,"minecraft:mutton":7,"minecraft:jungle_planks":237,"minecraft:waxed_copper_grate":4,"minecraft:pink_terracotta":111,"minecraft:obsidian":1070,"minecraft:honey_bottle":8,"minecraft:bricks":1,"minecraft:spruce_wood":395,"minecraft:lantern":305,"minecraft:blue_orchid":3,"minecraft:warped_nylium":999,"minecraft:item_frame":223,"minecraft:birch_button":48,"minecraft:deepslate_diamond_ore":75,"minecraft:golden_sword":3,"minecraft:birch_trapdoor":8,"minecraft:written_book":22,"minecraft:gold_block":885,"minecraft:pink_concrete_powder":225,"minecraft:diamond_boots":1,"minecraft:end_rod":28,"minecraft:dropper":123,"minecraft:wither_skeleton_skull":10,"minecraft:stone_pickaxe":9,"minecraft:oak_planks":1607,"minecraft:sandstone":1612,"minecraft:sugar_cane":2828,"minecraft:diamond_axe":1,"minecraft:bamboo_stairs":2,"minecraft:white_wool":391,"minecraft:netherite_leggings":2,"minecraft:light_blue_concrete":26907,"minecraft:mushroom_stew":4,"minecraft:yellow_concrete":124,"minecraft:crossbow":12,"minecraft:lingering_potion":185,"minecraft:deepslate_lapis_ore":3,"minecraft:end_stone":1940,"minecraft:creeper_spawn_egg":2,"minecraft:sticky_piston":877,"minecraft:black_terracotta":2298,"minecraft:dead_fire_coral_fan":3,"minecraft:lever":230,"minecraft:daylight_detector":3,"minecraft:dark_oak_log":142,"minecraft:bread":291,"minecraft:barrier":668,"minecraft:deepslate":1495,"minecraft:stripped_warped_hyphae":86,"minecraft:light_blue_concrete_powder":6751,"minecraft:dead_horn_coral_fan":23,"minecraft:cooked_rabbit":27,"minecraft:chain":45,"minecraft:smooth_stone_slab":11647,"minecraft:mossy_cobblestone_wall":294,"minecraft:stripped_cherry_log":1,"minecraft:bone_meal":2153,"minecraft:netherite_sword":10514,"minecraft:cherry_wood":1,"minecraft:white_tulip":11,"minecraft:flint_and_steel":385,"minecraft:redstone":1480,"minecraft:ender_chest":66,"minecraft:cooked_chicken":103,"minecraft:dirt":36862,"minecraft:prismarine_bricks":12988,"minecraft:bee_nest":1,"minecraft:spruce_fence":10,"minecraft:iron_hoe":52,"minecraft:wooden_axe":3,"minecraft:brown_terracotta":78,"minecraft:light_gray_stained_glass":502,"minecraft:oak_stairs":42,"minecraft:smooth_sandstone":239,"minecraft:black_stained_glass":47,"minecraft:soul_soil":4,"minecraft:lime_stained_glass":1,"minecraft:netherite_pickaxe":32803,"minecraft:minecart":110,"minecraft:cooked_beef":475,"minecraft:powder_snow_bucket":149,"minecraft:enchanted_golden_apple":39,"minecraft:bamboo_planks":1,"minecraft:iron_leggings":1,"minecraft:cobblestone_stairs":849,"minecraft:lodestone":2,"minecraft:snow_block":448,"minecraft:dark_oak_hanging_sign":1,"minecraft:baked_potato":617,"minecraft:cut_sandstone":6,"minecraft:vindicator_spawn_egg":1,"minecraft:waxed_copper_block":6,"minecraft:music_disc_cat":3,"minecraft:red_mushroom":9,"minecraft:spider_eye":53,"minecraft:bamboo_block":1,"minecraft:warped_planks":249,"minecraft:piston":690,"minecraft:gray_terracotta":703,"minecraft:black_wool":191,"minecraft:command_block":8,"minecraft:chicken":2,"minecraft:lapis_ore":22,"minecraft:detector_rail":48,"minecraft:jungle_stairs":291,"minecraft:magenta_concrete":637,"minecraft:end_crystal":40,"minecraft:pink_shulker_box":12,"minecraft:lapis_block":37,"minecraft:pumpkin_pie":1,"minecraft:wither_rose":5,"minecraft:gray_wool":1,"minecraft:pillager_spawn_egg":28,"minecraft:sculk_catalyst":6,"minecraft:birch_stairs":3,"minecraft:nether_brick_fence":261,"minecraft:bamboo_sign":5,"minecraft:spruce_slab":457,"minecraft:elytra":7,"minecraft:ladder":88,"minecraft:chest":616,"minecraft:brown_concrete":65,"minecraft:white_shulker_box":4,"minecraft:orange_wool":44,"minecraft:allium":4,"minecraft:jungle_slab":319,"minecraft:stripped_spruce_log":6,"minecraft:warden_spawn_egg":11,"minecraft:honey_block":194,"minecraft:honeycomb":6,"minecraft:netherite_shovel":12245,"minecraft:warped_hyphae":3002,"minecraft:black_stained_glass_pane":4,"minecraft:grass_block":10276,"minecraft:birch_sapling":232,"minecraft:copper_ore":205,"minecraft:wet_sponge":3,"minecraft:stone_brick_stairs":1225,"minecraft:snow":1984,"minecraft:red_stained_glass_pane":142,"minecraft:sweet_berries":356,"minecraft:furnace":206,"minecraft:potato":1246,"minecraft:dragon_head":1,"minecraft:dead_brain_coral_fan":1,"minecraft:light_blue_carpet":23,"minecraft:short_grass":2410,"minecraft:diorite":839,"minecraft:end_stone_bricks":2594,"minecraft:spruce_door":2,"minecraft:red_stained_glass":18,"minecraft:powered_rail":430,"minecraft:orange_tulip":11,"minecraft:lime_concrete_powder":171,"minecraft:oak_leaves":11204,"minecraft:cookie":96,"minecraft:dark_oak_trapdoor":56,"minecraft:sand":2541,"minecraft:blue_ice":2069,"minecraft:netherite_helmet":2,"minecraft:pumpkin_seeds":5,"minecraft:deepslate_tiles":1,"minecraft:cherry_hanging_sign":1,"minecraft:crying_obsidian":1,"minecraft:stripped_bamboo_block":1,"minecraft:stone_button":20,"minecraft:red_terracotta":139,"minecraft:lectern":25,"minecraft:diamond_ore":2183,"minecraft:soul_lantern":1,"minecraft:chiseled_tuff_bricks":1,"minecraft:fire_charge":4,"minecraft:white_stained_glass":10463,"minecraft:pink_stained_glass":72,"minecraft:ice":206,"minecraft:oak_hanging_sign":6,"minecraft:acacia_log":3,"minecraft:red_concrete":12,"minecraft:trial_key":7,"minecraft:netherrack":4939,"minecraft:anvil":9424,"minecraft:dragon_egg":2,"minecraft:target":10476,"minecraft:warped_wart_block":1,"minecraft:ancient_debris":3,"minecraft:wheat":23,"minecraft:chorus_flower":12,"minecraft:twisting_vines":71,"minecraft:crimson_hyphae":86,"minecraft:nether_brick_slab":948,"minecraft:glow_lichen":2252,"minecraft:blue_concrete":3331,"minecraft:nether_brick_stairs":104,"minecraft:shroomlight":76,"minecraft:red_shulker_box":17,"minecraft:flowering_azalea":1,"minecraft:bamboo_fence":1,"minecraft:spruce_button":1,"minecraft:iron_axe":882,"minecraft:brick_stairs":23,"minecraft:slime_block":2024,"minecraft:birch_hanging_sign":2,"minecraft:smooth_quartz":27,"minecraft:totem_of_undying":1,"minecraft:melon_seeds":14,"minecraft:purple_concrete":1816,"minecraft:glowstone":3533,"minecraft:tall_grass":90,"minecraft:beef":4,"minecraft:iron_trapdoor":469,"minecraft:goat_horn":12,"minecraft:cobbled_deepslate":210,"minecraft:orange_terracotta":50,"minecraft:observer":670,"minecraft:pointed_dripstone":4,"minecraft:crimson_stem":5,"minecraft:water_bucket":6563,"minecraft:light_blue_glazed_terracotta":77,"minecraft:prismarine_brick_slab":5,"minecraft:rabbit":1,"minecraft:cartography_table":11,"minecraft:red_mushroom_block":1,"minecraft:gilded_blackstone":12,"minecraft:pink_concrete":2130,"minecraft:mossy_cobblestone":1,"minecraft:lime_terracotta":21,"minecraft:comparator":175,"minecraft:vine":12,"minecraft:tnt":5677,"minecraft:oak_slab":538,"minecraft:crafting_table":61,"minecraft:birch_sign":317,"minecraft:cake":6,"minecraft:oak_log":2419,"minecraft:ender_eye":20,"minecraft:light":231,"minecraft:oxeye_daisy":61,"minecraft:iron_pickaxe":433,"minecraft:cyan_concrete":8086,"minecraft:crimson_nylium":236,"minecraft:chiseled_stone_bricks":573,"minecraft:cobblestone":17348,"minecraft:glass_pane":158,"minecraft:sandstone_slab":4,"minecraft:black_candle":2,"minecraft:brown_mushroom_block":18,"minecraft:end_portal_frame":12,"minecraft:kelp":30,"minecraft:candle":1,"minecraft:iron_shovel":76,"minecraft:dead_tube_coral_fan":14,"minecraft:oak_sign":105,"minecraft:diamond_hoe":276,"minecraft:shield":272,"minecraft:white_terracotta":1778,"minecraft:iron_sword":1405,"minecraft:bell":4,"minecraft:player_head":43,"minecraft:mangrove_hanging_sign":2,"minecraft:iron_chestplate":1,"minecraft:birch_pressure_plate":2,"minecraft:nether_bricks":128,"minecraft:carrot":2346,"minecraft:tuff":10,"minecraft:milk_bucket":1,"minecraft:glass":6180,"minecraft:cyan_terracotta":3155,"minecraft:coal_ore":286,"minecraft:quartz_slab":6260,"minecraft:tropical_fish_spawn_egg":90,"minecraft:hopper_minecart":100,"minecraft:stone_bricks":12504,"minecraft:bedrock":1585,"minecraft:spruce_hanging_sign":4,"minecraft:repeater":440,"minecraft:red_carpet":10,"minecraft:redstone_lamp":17,"minecraft:honeycomb_block":4,"minecraft:magma_block":488,"minecraft:hay_block":1,"minecraft:scaffolding":3551,"minecraft:large_fern":4,"minecraft:golden_boots":1,"minecraft:birch_leaves":4043,"minecraft:ender_pearl":1925,"minecraft:redstone_block":317,"minecraft:end_stone_brick_slab":1322,"minecraft:yellow_terracotta":14,"minecraft:light_gray_terracotta":376,"minecraft:sponge":508,"minecraft:note_block":38,"minecraft:dripstone_block":18,"minecraft:shulker_spawn_egg":4,"minecraft:stone_brick_wall":127,"minecraft:shears":162,"minecraft:redstone_torch":549,"minecraft:green_concrete":11,"minecraft:black_concrete":18837,"minecraft:firework_rocket":12717,"minecraft:melon_slice":853,"minecraft:birch_fence_gate":1396,"minecraft:mace":2047,"minecraft:string":24,"minecraft:light_gray_concrete":1738,"minecraft:gravel":14,"minecraft:grindstone":2,"minecraft:oak_fence":497,"minecraft:bamboo_mosaic_slab":1,"minecraft:jungle_leaves":5,"minecraft:purpur_block":1,"minecraft:deepslate_coal_ore":2,"minecraft:andesite":633,"minecraft:azalea":1,"minecraft:white_concrete":91531,"minecraft:chest_minecart":5,"minecraft:experience_bottle":205,"minecraft:tropical_fish_bucket":6,"minecraft:cobweb":5613,"minecraft:golden_pickaxe":6207,"minecraft:trident":3583,"minecraft:light_blue_terracotta":11461,"minecraft:spruce_planks":346,"minecraft:oak_door":3,"minecraft:spyglass":1527,"minecraft:white_carpet":41,"minecraft:hopper":1181,"minecraft:spruce_stairs":223,"minecraft:cobblestone_wall":569,"minecraft:diamond_helmet":1,"minecraft:shulker_box":457,"minecraft:oak_wood":1641,"minecraft:raw_iron_block":986,"minecraft:granite":735,"minecraft:light_blue_stained_glass":3,"minecraft:stone_brick_slab":3241,"minecraft:bamboo_raft":4,"minecraft:red_tulip":7,"minecraft:bookshelf":3,"minecraft:yellow_stained_glass":91,"minecraft:acacia_slab":451,"minecraft:crimson_planks":18,"minecraft:golden_carrot":69,"minecraft:bamboo_chest_raft":90,"minecraft:emerald_block":712,"minecraft:wolf_spawn_egg":8,"minecraft:white_stained_glass_pane":3620,"minecraft:cooked_mutton":271,"minecraft:pink_tulip":12,"minecraft:iron_ore":1,"minecraft:netherite_chestplate":3,"minecraft:glass_bottle":572,"minecraft:black_shulker_box":6,"minecraft:stonecutter":3,"minecraft:beacon":10,"minecraft:cobblestone_slab":3087,"minecraft:glow_item_frame":37,"minecraft:piglin_head":1,"minecraft:activator_rail":31,"minecraft:acacia_stairs":452,"minecraft:apple":5,"minecraft:map":96,"minecraft:netherite_axe":8737,"minecraft:fishing_rod":277,"minecraft:cherry_stairs":1,"minecraft:white_banner":43,"minecraft:bucket":4466,"minecraft:magenta_glazed_terracotta":11,"minecraft:yellow_bed":3,"minecraft:smooth_stone":10931,"minecraft:splash_potion":393},"minecraft:killed":{"minecraft:cod":5,"minecraft:guardian":18,"minecraft:tropical_fish":5,"minecraft:elder_guardian":3,"minecraft:salmon":51,"minecraft:iron_golem":47,"minecraft:ender_dragon":4,"minecraft:pillager":164,"minecraft:zombie":1561,"minecraft:donkey":7,"minecraft:endermite":37,"minecraft:vindicator":1,"minecraft:snow_golem":4,"minecraft:warden":8,"minecraft:rabbit":24,"minecraft:frog":3,"minecraft:ravager":1,"minecraft:breeze":18,"minecraft:zombified_piglin":120,"minecraft:witch":24,"minecraft:spider":961,"minecraft:wither":2,"minecraft:bee":10,"minecraft:silverfish":7,"minecraft:piglin_brute":8,"minecraft:piglin":191,"minecraft:zombie_villager":27,"minecraft:sheep":176,"minecraft:trader_llama":45,"minecraft:ghast":6,"minecraft:armadillo":3,"minecraft:slime":1340,"minecraft:drowned":11,"minecraft:hoglin":105,"minecraft:squid":33,"minecraft:wither_skeleton":1,"minecraft:villager":400,"minecraft:shulker":103,"minecraft:skeleton":912,"minecraft:fox":5,"minecraft:chicken":135,"minecraft:cat":24,"minecraft:magma_cube":12,"minecraft:cow":108,"minecraft:zoglin":1,"minecraft:horse":67,"minecraft:wandering_trader":24,"minecraft:enderman":26246,"minecraft:wolf":18,"minecraft:pig":123,"minecraft:strider":1,"minecraft:creeper":736,"minecraft:stray":142,"minecraft:blaze":4,"minecraft:bogged":58,"minecraft:phantom":40,"minecraft:bat":49}},"DataVersion":3953}